Workbook

Sheet Overview
A1: Attention to Detail (Textual) – Skills Assessment
A3: Test name | B3: Attention to Detail (Textual)
A4: Duration | B4: 12 minutes
A5: Number of questions | B5: =Questions!$B$19 -> 15
A6: Question format | B6: Multiple choice (single answer) – matching records and snippets, counting differences between two texts, spotting contradictions between sentences
A7: Level | B7: Intermediate
A8: Language of instructions | B8: English (localisable – when translating, re-verify every key because word counts and spellings change)
A9: Overview | B9: This Attention to Detail (Textual) test evaluates candidates' attention to textual detail while processing information. It helps identify candidates who can thoroughly and carefully handle intricate processes.
A10: Skills covered | B10: 1. Matching information (Q1–Q5) – identifying identical vs. near-identical text, codes, records and counts 2. Comparing statements for differences (Q6–Q10) – counting word, number and punctuation differences between two versions of a text 3. Checking the consistency of information (Q11–Q15) – spotting facts or details in one sentence that contradict another
A11: Relevant for | B11: Any role that requires attention to detail – customer care, office assistant, administrator, bookkeeper, data entry, QA, compliance – and as a general focus check for entry-level roles.
A12: Description | B12: Noticing little things can have a big impact. From grammatical mistakes that give an impression of unprofessionalism to mistakes in numbers and data that cause serious errors, paying attention to detail is an important skill for every professional. This test evaluates candidates' ability to consider details by presenting tasks that require them to match information, compare statements and check the consistency of information. It provides insight into candidates' alertness by asking them to identify errors, omissions or inconsistencies in the information presented. Candidates who score well can process textual information and arrive at the correct answer without losing sight of small details. Errors are of the kind that occur in real administrative work: transposed digits, changed units, a missing apostrophe, a day that does not match its date, a total that does not match its parts.
A13: Question distribution | B13: 5 questions per skill area. Difference-count items use a spread of answers (0, 1, 2, 3) so candidates cannot assume every pair differs.
A14: Timing guidance | B14: 12 min ÷ 15 = 48 seconds per question. Consistency items (Q11–Q15) take longest; difference items are quick if the candidate is systematic.
A15: Scoring | B15: 1 point per correct answer, no negative marking. Score = correct ÷ 15. See 'Rubric'.
A16: Quality control | B16: All keys in this workbook were computed programmatically (set comparison for unique snippets, token-level diff for difference counts, calendar lookup for day/date items) and are reproducible – see 'Key verification' tab. Re-run the check after any edit.

Sheet Questions
A1: ID | B1: Skill area | C1: Question type | D1: Instruction (shown to candidate) | E1: Passage / material (shown to candidate) | F1: Question stem | G1: Attachment | H1: Option A | I1: Option B | J1: Option C | K1: Option D | L1: Key | M1: Key answer (text) | N1: Rationale / what differs | O1: Difficulty
A2: Q1 | B2: Matching information | C2: Count unique versions | D2: Review the information carefully. Two items match only if they use identical words, numbers, symbols and punctuation marks. | E2: Your coworker drafted a message containing the following four snippets. You are checking whether they match each other exactly. Snippet 1: Order A-2291: 12 units of Model X200 shipped 14 Aug; tracking no. 7783 4410 2; invoice total €1,860.00. Snippet 2: Order A-2291: 12 units of Model X200 shipped 14 Aug; tracking no. 7783 4410 2; invoice total €1,680.00. Snippet 3: Order A-2291: 12 units of Model X200 shipped 14 Aug; tracking no. 7783 4410 2; invoice total €1,860.00. Snippet 4: Order A-2291: 12 units of Model X200 shipped 14 Aug; tracking no. 7783 4401 2; invoice total €1,860.00. | F2: How many different unique snippet versions are included in the draft? | G2: None | H2: One | I2: Two | J2: Three | K2: Four | L2: C | M2: Three | N2: Snippets 1 and 3 are identical. Snippet 2 changes €1,860.00 → €1,680.00 (transposed digits). Snippet 4 changes tracking 4410 → 4401. Three unique versions. | O2: Medium
A3: Q2 | B3: Matching information | C3: Match a reference record | D3: Review the information carefully. Two items match only if they use identical words, numbers, symbols and punctuation marks. | E3: Reference record on file: Anika Berg, 47 Larkspur Road, Flat 3B, Leeds LS6 2QT Which of the options below is identical to the reference record? | F3: Select the option that matches the reference record exactly. | G3: None | H3: Anika Berg, 47 Larkspur Road, Flat 3B, Leeds LS6 2QT | I3: Anika Berg, 47 Larkspur Rd, Flat 3B, Leeds LS6 2QT | J3: Anika Berg, 47 Larkspur Road, Flat 38, Leeds LS6 2QT | K3: Anika Berg, 47 Larkspur Road, Flat 3B, Leeds LS6 2OT | L3: A | M3: Anika Berg, 47 Larkspur Road, Flat 3B, Leeds LS6 2QT | N3: B abbreviates Road → Rd; C changes Flat 3B → 38; D changes postcode 2QT → 2OT (letter O for Q). | O3: Easy
A4: Q3 | B4: Matching information | C4: Cross-check two lists | D4: Review the information carefully. Two items match only if they use identical words, numbers, symbols and punctuation marks. | E4: Approved invoice numbers: INV-30417 INV-30471 INV-30714 INV-30741 Invoices received in today's batch: INV-30417 INV-30174 INV-30741 INV-30471 INV-31047 INV-30714 | F4: How many of the invoices received today are on the approved list? | G4: None | H4: Two | I4: Three | J4: Four | K4: Five | L4: C | M4: Four | N4: Matches: 30417, 30741, 30471, 30714. Non-matches are digit transpositions: 30174, 31047. Four. | O4: Medium
A5: Q4 | B5: Matching information | C5: Match a product code | D5: Review the information carefully. Two items match only if they use identical words, numbers, symbols and punctuation marks. | E5: Reference SKU: TM-2048-BLK-XL | F5: Which option is identical to the reference SKU? | G5: None | H5: TM-2084-BLK-XL | I5: TM-2048-BLK-XL | J5: TM-2048-BKL-XL | K5: TM-2048-BLK-LX | L5: B | M5: TM-2048-BLK-XL | N5: A transposes 2048 → 2084; C transposes BLK → BKL; D transposes XL → LX. | O5: Easy
A6: Q5 | B6: Matching information | C6: Count exact occurrences | D6: Review the information carefully. Two items match only if they use identical words, numbers, symbols and punctuation marks. | E6: Passage: "Please send the report to Finance by Friday. Once the report is approved, the summary will be reported to the board. Last quarter's reports were late, so this report must be on time. If you need the template, the reporting team can share it." | F6: How many times does the exact word "report" appear in the passage? (Do not count "reports", "reported" or "reporting".) | G6: None | H6: Two | I6: Three | J6: Four | K6: Five | L6: B | M6: Three | N6: Exact matches: 'the report to Finance', 'the report is approved', 'this report must'. Excluded: reported, reports, reporting. | O6: Medium
A7: Q6 | B7: Comparing statements for differences | C7: Count differences (words & punctuation) | D7: Compare the two texts word by word. Count every word, number or punctuation mark that differs (a changed, added or missing item counts as one difference). | E7: Sentence A: Please confirm that the three invoices attached to this email have been forwarded to the accounts team before Thursday's deadline. Sentence B: Please confirm that the three invoices attached to this email have been forwarded to the account team before Thursdays deadline. | F7: How many words and punctuation marks are different between the two sentences? | G7: None | H7: There are 0 differences between Sentence A and Sentence B. | I7: There is 1 difference between Sentence A and Sentence B. | J7: There are 2 differences between Sentence A and Sentence B. | K7: There are 3 differences between Sentence A and Sentence B. | L7: C | M7: There are 2 differences between Sentence A and Sentence B. | N7: accounts → account; Thursday's → Thursdays (missing apostrophe). Two. | O7: Medium
A8: Q7 | B8: Comparing statements for differences | C8: Count differences (identical pair) | D8: Compare the two texts word by word. Count every word, number or punctuation mark that differs (a changed, added or missing item counts as one difference). | E8: Sentence A: The supplier will deliver the replacement parts on 22 September, and installation is scheduled for the following Monday. Sentence B: The supplier will deliver the replacement parts on 22 September, and installation is scheduled for the following Monday. | F8: How many words and punctuation marks are different between the two sentences? | G8: None | H8: There are 0 differences between Sentence A and Sentence B. | I8: There is 1 difference between Sentence A and Sentence B. | J8: There are 2 differences between Sentence A and Sentence B. | K8: There are 3 differences between Sentence A and Sentence B. | L8: A | M8: There are 0 differences between Sentence A and Sentence B. | N8: The sentences are identical. Tests whether candidates verify rather than assume a difference must exist. | O8: Medium
A9: Q8 | B9: Comparing statements for differences | C9: Count differences (numeric) | D9: Compare the two texts word by word. Count every word, number or punctuation mark that differs (a changed, added or missing item counts as one difference). | E9: Version A: Attendance: 14; budget approved: €12,500; next review: 3 March; action items: 7; owner: R. Costa. Version B: Attendance: 14; budget approved: €12,900; next review: 3 March; action items: 7; owner: R. Costa. | F9: How many differences are there between Version A and Version B? | G9: None | H9: 0 | I9: 1 | J9: 2 | K9: 3 | L9: B | M9: 1 | N9: €12,500 → €12,900 only. Everything else, including 'R. Costa', is identical. | O9: Easy
A10: Q9 | B10: Comparing statements for differences | C10: Identify the differing field | D10: Compare the two texts word by word. Count every word, number or punctuation mark that differs (a changed, added or missing item counts as one difference). | E10: Record A Name: Daniel Okafor Street: 118 Mill Lane City: Norwich Postcode: NR2 4PA Phone: 01603 555 018 Record B Name: Daniel Okafor Street: 118 Mill Lane City: Norwich Postcode: NR2 4PA Phone: 01603 555 081 | F10: Which field is different between Record A and Record B? | G10: None | H10: Street | I10: Postcode | J10: Phone | K10: None – the records are identical | L10: C | M10: Phone | N10: Phone ends 018 in A and 081 in B (transposed digits). Street and postcode are identical. | O10: Easy
A11: Q10 | B11: Comparing statements for differences | C11: Count differences (paragraph) | D11: Compare the two texts word by word. Count every word, number or punctuation mark that differs (a changed, added or missing item counts as one difference). | E11: Text A: Our office will be closed on Monday 4 May for the public holiday. Urgent requests should be sent to support@northwind.example, and a member of the team will respond within 24 hours. Text B: Our office will be closed on Monday 6 May for the public holiday. Urgent requests should be send to support@northwind.example, and a member of the team will respond within 48 hours. | F11: How many words, numbers or punctuation marks are different between Text A and Text B? | G11: None | H11: 1 | I11: 2 | J11: 3 | K11: 4 | L11: C | M11: 3 | N11: 4 May → 6 May; sent → send; 24 hours → 48 hours. Three. The email address is identical and acts as a distractor. | O11: Hard
A12: Q11 | B12: Checking the consistency of information | C12: Consistency – procedure | D12: Review the sentences for textual consistency. Consistency means that the facts and/or details in each sentence do not contradict facts or details in the other sentences. Do not use outside knowledge; judge only what the text says. | E12: Sentence 1: All expense claims must be submitted through the online portal by the 25th of each month. Sentence 2: Claims received after the 25th will be processed in the following month's payroll. Sentence 3: Paper claim forms handed to the finance office are also accepted until the 25th. | F12: Which of the following best describes the consistency of the sentences? | G12: None | H12: All three sentences are consistent. | I12: Sentences 1 and 2 are inconsistent with each other. | J12: Sentences 1 and 3 are inconsistent with each other. | K12: Sentences 2 and 3 are inconsistent with each other. | L12: C | M12: Sentences 1 and 3 are inconsistent with each other. | N12: Sentence 1 says claims 'must' go through the portal; Sentence 3 says paper forms are also accepted. Sentence 2 is consistent with both. | O12: Medium
... A16: Q15 | B16: Checking the consistency of information | C16: Consistency – policy | D16: Review the sentences for textual consistency. Consistency means that the facts and/or details in each sentence do not contradict facts or details in the other sentences. Do not use outside knowledge; judge only what the text says. | E16: Sentence 1: Customers may return unused items within 30 days of delivery for a full refund. Sentence 2: Items returned after 30 days are eligible for store credit only. Sentence 3: Refunds for returns made 45 days after delivery are paid to the original payment method within 5 working days. | F16: Which of the following best describes the consistency of the sentences? | G16: None | H16: All three sentences are consistent. | I16: Sentence 1 is inconsistent with sentences 2 and 3. | J16: Sentence 2 is inconsistent with sentences 1 and 3. | K16: Sentence 3 is inconsistent with sentences 1 and 2. | L16: D | M16: Sentence 3 is inconsistent with sentences 1 and 2. | N16: A return at 45 days is 'after 30 days', so per Sentence 2 only store credit applies – yet Sentence 3 promises a refund to the payment method, contradicting both 1 and 2. | O16: Hard
A18: Summary
A19: Total questions | B19: =COUNTA(A2:A16) -> 15
A20: Matching information | B20: =COUNTIF(B2:B16,"Matching information") -> 5
A21: Comparing statements for differences | B21: =COUNTIF(B2:B16,"Comparing statements for differences") -> 5
A22: Checking the consistency of information | B22: =COUNTIF(B2:B16,"Checking the consistency of information") -> 5
A24: Notes: Render passages in a monospaced or clearly kerned font so that digit and letter differences are visible. Do not shuffle options for count items (Q1, Q3, Q5–Q8, Q10) – keep them in ascending order. Never let the platform auto-correct or 'smart-quote' the passages; that would silently change the keys.

Sheet Key verification
A1: ID | B1: Verification method | C1: Computed result | D1: Key in 'Questions' | E1: Match?
A2: Q1 | B2: Python: len(set(snippets)) | C2: 3 | D2: =Questions!L2 -> C | E2: =IF(D2="C","OK","CHECK") -> OK
A3: Q2 | B3: Python: option == reference string | C3: A | D3: =Questions!L3 -> A | E3: =IF(D3="A","OK","CHECK") -> OK
A4: Q3 | B4: Python: sum(item in approved_set for item in batch) | C4: 4 | D4: =Questions!L4 -> C | E4: =IF(D4="C","OK","CHECK") -> OK
A5: Q4 | B5: Python: option == reference SKU | C5: B | D5: =Questions!L5 -> B | E5: =IF(D5="B","OK","CHECK") -> OK
A6: Q5 | B6: Python: len(re.findall(r'\breport\b', passage)) | C6: 3 | D6: =Questions!L6 -> B | E6: =IF(D6="B","OK","CHECK") -> OK
A7: Q6 | B7: Python: token-level difflib count | C7: 2 | D7: =Questions!L7 -> C | E7: =IF(D7="C","OK","CHECK") -> OK
A8: Q7 | B8: Python: token-level difflib count | C8: 0 | D8: =Questions!L8 -> A | E8: =IF(D8="A","OK","CHECK") -> OK
A9: Q8 | B9: Python: token-level difflib count | C9: 1 | D9: =Questions!L9 -> B | E9: =IF(D9="B","OK","CHECK") -> OK
A10: Q9 | B10: Python: fields where A[k] != B[k] | C10: Phone | D10: =Questions!L10 -> C | E10: =IF(D10="C","OK","CHECK") -> OK
A11: Q10 | B11: Python: token-level difflib count | C11: 3 | D11: =Questions!L11 -> C | E11: =IF(D11="C","OK","CHECK") -> OK
A12: Q11 | B12: Manual: 'must … online portal' vs 'paper forms also accepted' | C12: 1 vs 3 | D12: =Questions!L12 -> C | E12: =IF(D12="C","OK","CHECK") -> OK
A13: Q12 | B13: Python: datetime.date(2026,10,6).strftime('%A') == 'Tuesday'; times ordered 9:15 < 9:30 < 12:30 | C13: consistent | D13: =Questions!L13 -> A | E13: =IF(D13="A","OK","CHECK") -> OK
A14: Q13 | B14: Python: datetime.date(2026,10,14).strftime('%A') == 'Wednesday' (so 'Thursday 14 October' is wrong) | C14: 3 vs 1 | D14: =Questions!L14 -> D | E14: =IF(D14="D","OK","CHECK") -> OK
A15: Q14 | B15: Arithmetic: 3 × 4 = 12 ≠ 14; 3 × 10 = 30 ✓ | C15: 1 vs 3 | D15: =Questions!L15 -> C | E15: =IF(D15="C","OK","CHECK") -> OK
A16: Q15 | B16: Logic: 45 > 30 ⇒ store credit only (S2) vs refund (S3) | C16: 3 vs 1 and 2 | D16: =Questions!L16 -> D | E16: =IF(D16="D","OK","CHECK") -> OK
A18: Column D pulls the live key from the Questions tab; column E confirms it matches the value computed when the workbook was generated. If you edit a passage, re-run the generator script (or recheck by hand) and update column C.

Sheet Rubric
A1: Assessment rubric – Attention to Detail (Textual)
A3: Scoring rules
A4: 1. 1 point per correct answer; 0 for incorrect, skipped or timed-out items. No negative marking.
A5: 2. Overall score = points ÷ total questions (cell B12). Report the three sub-scores.
A6: 3. Timer: 12 minutes total. Speed matters less than accuracy here; do not shorten the timer to add pressure – that measures stress tolerance, not attention to detail.
A7: 4. Present items in random order across skill areas. Keep count options in ascending order.
A8: 5. Because keys depend on exact characters, disable auto-correct, smart quotes and automatic number formatting in the delivery platform, and re-verify keys after any translation.
A9: 6. Combine with a work-sample task (e.g. proofreading a real document from the role) for final-stage candidates; this test screens, it does not certify.
A11: Score calculator (enter correct answers in B12)
A12: Correct answers | B12: 12 | C12: ← example value, edit this cell
A13: Total questions | B13: =Questions!$B$19 -> 15
A14: Score (%) | B14: =IF(B13=0,0,B12/B13) -> 0.8
A15: Band | B15: =IF(B14>=$A$20,$B$20,IF(B14>=$A$21,$B$21,IF(B14>=$A$22,$B$22,$B$23))) -> Good
A18: Score bands
A19: Min score | B19: Band | C19: Correct (of 15) | D19: Interpretation | E19: Recommended action
A20: 0.93 | B20: Excellent | C20: 14–15 | D20: Catches transposed digits, missing punctuation and cross-sentence contradictions reliably, and does not invent errors where there are none. | E20: Progress. Suitable for bookkeeping, data entry, compliance and QA roles without further detail screening.
A21: 0.73 | B21: Good | C21: 11–13 | D21: Reliable on direct comparisons; occasional misses on multi-fact consistency items or on 'no difference' traps. | E21: Progress. Review which sub-score is weakest and include one proofreading task in the interview.
A22: 0.53 | B22: Fair | C22: 8–10 | D22: Notices obvious differences but misses subtle ones (single digit, apostrophe, day/date) or over-reports differences. | E22: Progress only for roles where detail work is checked by a second person or by system validation.
A23: 0 | B23: Below expectation | C23: 0–7 | D23: Frequent misses; likely to introduce or overlook data errors in administrative work. | E23: Do not progress for detail-critical roles.
A26: Skill-level rubric
A27: Skill area | B27: Questions | C27: What a strong candidate does | D27: Weak signal (≤2/5) | E27: Error types covered
A28: Matching information | B28: Q1–Q5 | C28: Compares character by character, checks every field of a record, counts exact strings without being distracted by near-matches. | D28: Accepts 'close enough' matches; miscounts near-duplicates. | E28: Transposed digits, abbreviations, letter/digit look-alikes (O/Q, 3B/38), inflected word forms.
A29: Comparing statements for differences | B29: Q6–Q10 | C29: Works systematically through both texts, counts each differing token once, and correctly reports zero when texts are identical. | D29: Finds one difference and stops; reports differences in identical texts; double-counts. | E29: Word substitutions, missing apostrophes, changed numbers and dates, unchanged decoys (email addresses, names).
A30: Checking the consistency of information | B30: Q11–Q15 | C30: Holds facts from earlier sentences in mind and tests each later sentence against them, including arithmetic and calendar checks. | D30: Judges sentences in isolation; misses numeric or day/date contradictions; flags consistent text as inconsistent. | E30: Procedural contradictions, day/date mismatch, part/total arithmetic, policy threshold conflicts, fully consistent set (control item).
A32: Legend: blue text / yellow fill = editable inputs (band thresholds A20:A23, correct answers B12). Black = formulas.

Sheet Open data sources
A1: Resource | B1: Type | C1: Licence | D1: Use it for | E1: URL
A2: GitHub Typo Corpus | B2: 350k+ real typo/correction pairs from commit histories | C2: CC BY 4.0 (metadata) – check per-repo licences for text | D2: Realistic single-character and word-level errors for difference items | E2: https://github.com/mhagiwara/github-typo-corpus
A3: Wikipedia revision history / WikEd Error Corpus | B3: Sentence pairs before/after edits | C3: CC BY-SA 3.0/4.0 | D3: Authentic before/after sentence pairs for 'count the differences' items | E3: https://dumps.wikimedia.org/ | https://github.com/snukky/wikiedits
A4: BEA-2019 / W&I+LOCNESS grammatical error corpora | B4: Learner sentences with corrections | C4: Research use – check licence | D4: Grammar-level differences (apostrophes, agreement) for comparison items | E4: https://www.cl.cam.ac.uk/research/nl/bea2019st/
A5: Faker (Python library) | B5: Synthetic names, addresses, phone numbers, SKUs, invoice numbers | C5: MIT | D5: Generate unlimited realistic records for matching items without using real personal data | E5: https://github.com/joke2k/faker
A6: OpenAddresses | B6: Open address data | C6: Various open licences (mostly CC BY / ODbL) | D6: Real address formats for record-matching items (anonymise names) | E6: https://openaddresses.io/
A7: Enron Email Dataset (CMU) | B7: Real workplace emails | C7: Public domain | D7: Realistic business-email phrasing for consistency items – paraphrase; do not use real names | E7: https://www.cs.cmu.edu/~enron/
A8: US Government plain-language sample documents (plainlanguage.gov) | B8: Policy and procedure text | C8: Public domain | D8: Source material for policy-consistency items | E8: https://www.plainlanguage.gov/examples/
A9: Python difflib + datetime (standard library) | B9: Tooling | C9: PSF licence | D9: Compute and verify keys for difference counts and day/date items (method used in this workbook) | E9: https://docs.python.org/3/library/difflib.html
A11: All passages, records and codes in this workbook are fictional and original. Names and addresses do not refer to real people.
